pyftx/__init__.py
pyftx/authentication.py
pyftx/client.py
pyftx/enums.py
pyftx/exceptions.py
pyftx/streams.py
pyftx/threaded_stream.py
pyftx/timer.py
python_ftx_api-0.0.6.dist-info/LICENSE
python_ftx_api-0.0.6.dist-info/METADATA
python_ftx_api-0.0.6.dist-info/WHEEL
python_ftx_api-0.0.6.dist-info/top_level.txt
python_ftx_api-0.0.6.dist-info/zip-safe
python_ftx_api-0.0.6.dist-info/RECORD
