Metadata-Version: 2.1
Name: python-ftx-api
Version: 0.0.6
Summary: FTX python wrapper with rest API, websocket API.
Home-page: https://gitlab.com/cuongitl/python-ftx-api
Author: Cuongitl
Author-email: 
License: MIT
Keywords: Cuongitl ftx api restapi websocketapi example-python-ftx
Platform: UNKNOWN
Classifier: Intended Audience :: Developers
Classifier: License :: OSI Approved :: MIT License
Classifier: Operating System :: OS Independent
Classifier: Programming Language :: Python :: 3
Classifier: Programming Language :: Python
Classifier: Topic :: Software Development :: Libraries :: Python Modules
Requires-Python: >=3.6
License-File: LICENSE
Requires-Dist: requests
Requires-Dist: aiohttp
Requires-Dist: websockets
Requires-Dist: loguru
